ynx/__init__.py
ynx/__main__.py
ynx/cli/develop.py
ynx/impl/convert.py
ynx-0.0.2.dist-info/METADATA
ynx-0.0.2.dist-info/WHEEL
ynx-0.0.2.dist-info/RECORD
