Metadata-Version: 2.4
Name: ynx
Version: 0.0.2
Summary: Convert YAML ↔︎ Nix (Python side)
Requires-Python: >=3.11
Requires-Dist: ruamel-yaml
Requires-Dist: typer
